glsm/__init__.py
glsm/non_predictive/__init__.py
glsm/non_predictive/features.py
glsm/non_predictive/model.py
glsm-0.1.4.dist-info/licenses/LICENSE
glsm-0.1.4.dist-info/METADATA
glsm-0.1.4.dist-info/WHEEL
glsm-0.1.4.dist-info/top_level.txt
glsm-0.1.4.dist-info/RECORD
