Metadata-Version: 2.4
Name: glsm
Version: 0.1.4
Summary: A Python package that simplifies the process of building lead scoring models.
Author: Victor Valar
Author-email: <valar@victorvalar.tech>
License: LICENSE.txt
Keywords: python,lead score,modeling,lead generation,lead scoring,lead scoring model
Classifier: Development Status :: 4 - Beta
Classifier: Intended Audience :: Developers
Classifier: Programming Language :: Python :: 3
Classifier: Operating System :: Unix
Classifier: Operating System :: MacOS :: MacOS X
Classifier: Operating System :: Microsoft :: Windows
License-File: LICENSE
Requires-Dist: colorama==0.4.6
Requires-Dist: exceptiongroup==1.1.1
Requires-Dist: iniconfig==2.0.0
Requires-Dist: numpy==1.25.0
Requires-Dist: packaging==23.1
Requires-Dist: pluggy==1.2.0
Requires-Dist: python-dateutil==2.8.2
Requires-Dist: pytz==2023.3
Requires-Dist: six==1.16.0
Requires-Dist: tomli==2.0.1
Requires-Dist: typing-extensions==4.7.0
Requires-Dist: tzdata==2023.3
Requires-Dist: pandas
Requires-Dist: pydantic==2.4.0
Requires-Dist: pex
Requires-Dist: toml
Dynamic: author
Dynamic: author-email
Dynamic: classifier
Dynamic: description
Dynamic: description-content-type
Dynamic: keywords
Dynamic: license
Dynamic: license-file
Dynamic: requires-dist
Dynamic: summary
